pyuseful/__init__.py
pyuseful/classtools/__init__.py
pyuseful/classtools/immutable.py
pyuseful/classtools/message.py
pyuseful/classtools/postinit.py
pyuseful/classtools/require.py
pyuseful/decorators/__init__.py
pyuseful/decorators/postinit.py
pyuseful/decorators/require.py
pyuseful/decorators/thread.py
pyuseful/decorators/timing.py
pyuseful/filetools/__init__.py
pyuseful/filetools/misc.py
pyuseful/filetools/splicer.py
pyuseful-0.0.6.dist-info/LICENSE
pyuseful-0.0.6.dist-info/METADATA
pyuseful-0.0.6.dist-info/WHEEL
pyuseful-0.0.6.dist-info/top_level.txt
pyuseful-0.0.6.dist-info/RECORD
