Metadata-Version: 2.1
Name: pyuseful
Version: 0.0.6
Summary: A collection of useful tools
Author-email: sikvelsigma <sikvelsigma@yandex.ru>
License: MIT License        
Project-URL: Homepage, https://github.com/sikvelsigma/pytools-utils
Project-URL: Bug Tracker, https://github.com/sikvelsigma/pytools-utils/issues
Classifier: Programming Language :: Python :: 3
Classifier: License :: OSI Approved :: MIT License
Classifier: Operating System :: OS Independent
Requires-Python: >=3.9
License-File: LICENSE
